pythrel/__init__.py
pythrel/adapters/__init__.py
pythrel/adapters/postgres.py
pythrel/adapters/sqlite.py
pythrel/database.py
pythrel-0.1.1.dist-info/LICENSE
pythrel-0.1.1.dist-info/METADATA
pythrel-0.1.1.dist-info/WHEEL
pythrel-0.1.1.dist-info/entry_points.txt
pythrel-0.1.1.dist-info/RECORD
