Metadata-Version: 2.1
Name: pythrel
Version: 0.1.1
Summary: Simple SQL ORM with support for several DB providers
Home-page: https://github.com/iTecAI/pythrel
License: MIT
Author: Dax Harris
Author-email: matteovh@gmail.com
Requires-Python: >=3.10,<4.0
Classifier: License :: OSI Approved :: MIT License
Classifier: Programming Language :: Python :: 3
Classifier: Programming Language :: Python :: 3.10
Classifier: Programming Language :: Python :: 3.11
Requires-Dist: psycopg (>=3.1.10,<4.0.0)
Requires-Dist: pydantic (>=2.3.0,<3.0.0)
Project-URL: Repository, https://github.com/iTecAI/pythrel
